annetbox/__init__.py
annetbox/py.typed
annetbox/base/__init__.py
annetbox/base/client_async.py
annetbox/base/client_sync.py
annetbox/base/exceptions.py
annetbox/base/models.py
annetbox/v24/__init__.py
annetbox/v24/client_async.py
annetbox/v24/client_sync.py
annetbox/v24/models.py
annetbox/v37/__init__.py
annetbox/v37/client_async.py
annetbox/v37/client_sync.py
annetbox/v37/models.py
annetbox/v41/__init__.py
annetbox/v41/client_async.py
annetbox/v41/client_sync.py
annetbox/v41/models.py
annetbox/v42/__init__.py
annetbox/v42/client_async.py
annetbox/v42/client_sync.py
annetbox/v42/models.py
annetbox-0.8.0.dist-info/licenses/LICENSE
annetbox-0.8.0.dist-info/METADATA
annetbox-0.8.0.dist-info/WHEEL
annetbox-0.8.0.dist-info/top_level.txt
annetbox-0.8.0.dist-info/RECORD
