Metadata-Version: 2.4
Name: annetbox
Version: 0.8.0
Summary: Annet Netbox client
Author-email: Andrey Tikhonov <tishka17@nebius.com>
License: MIT
Project-URL: Source, https://github.com/annetutil/annetbox
Project-URL: Homepage, https://github.com/annetutil/annetbox
Project-URL: Bug Tracker, https://github.com/annetutil/annetbox/issues
Classifier: Programming Language :: Python :: 3.10
Classifier: Programming Language :: Python :: 3.11
Classifier: Programming Language :: Python :: 3.12
Classifier: Topic :: Software Development :: Libraries
Classifier: Typing :: Typed
Classifier: Intended Audience :: Developers
Classifier: License :: OSI Approved :: MIT License
Classifier: Operating System :: OS Independent
Requires-Python: >=3.10
License-File: LICENSE
Requires-Dist: adaptix~=3.0.0b2
Requires-Dist: dataclass-rest~=0.4
Requires-Dist: python-dateutil~=2.8
Provides-Extra: sync
Requires-Dist: requests; extra == "sync"
Provides-Extra: async
Requires-Dist: aiohttp; extra == "async"
Dynamic: license-file
